{
  "pop": [
    {
      "page": 1,
      "list": [
        {
          "id": "pop1",
          "tittle": "【白宇帆明星同款】哈吉斯HAZZYS 2021秋冬新款中长款男士外套羽绒服男ASFZU01DX80Y 米色BI 175/96A",
          "price": 3391,
          "star": 1560,
          "url": "https://m.360buyimg.com/babel/s309x309_jfs/t1/206381/33/11993/6014/616fc634Ea138ff75/8d16edf00bd22f9d.jpg!cc_501x501!q70.dpg"
        },
        {
          "id": "pop2",
          "tittle": "Teenmix\/天美意短靴女厚底马丁靴女冬季2021新品商场同款靴子女单靴CZK40DD1 米色 37",
          "price": 1009,
          "star": 192,
          "url": "https://m.360buyimg.com/babel/s309x309_jfs/t1/110485/16/16014/90678/6151947fEe85cb718/bc3cd0d279e57efe.jpg!cc_501x501!q70.dpg"
        },
        {
          "id": "pop3",
          "tittle": "【刘亚仁同款】速写男装2021秋新品夹克明星同款水洗立领时尚潮9L9600360 990牛仔黑 M",
          "price": 2395,
          "star": 310,
          "url": "https://m.360buyimg.com/babel/s309x309_jfs/t1/199976/1/10682/424290/615557dbE25a5cb86/b939d3688e22e025.jpg!cc_501x501!q70.dpg"
        },
        {
          "id": "pop4",
          "tittle": "ONLY2021秋季新款杜邦三防中长款收腰90白鸭绒羽绒服女|121423005 H1Z 黑色BLACK 165/84A/M",
          "price": 1199,
          "star": 4000,
          "url": "https://m.360buyimg.com/babel/s309x309_jfs/t1/201407/7/8800/120721/6151a09eE7c5dfb56/c774006216420e37.jpg!cc_501x501!q70.dpg"
        },
        {
          "id": "pop5",
          "tittle": "【白宇帆明星同款】哈吉斯HAZZYS 2021秋冬新款中长款男士外套羽绒服男ASFZU01DX80Y 米色BI 175/96A",
          "price": 3391,
          "star": 1560,
          "url": "https://m.360buyimg.com/babel/s309x309_jfs/t1/206381/33/11993/6014/616fc634Ea138ff75/8d16edf00bd22f9d.jpg!cc_501x501!q70.dpg"
        },
        {
          "id": "pop6",
          "tittle": "Teenmix\/天美意短靴女厚底马丁靴女冬季2021新品商场同款靴子女单靴CZK40DD1 米色 37",
          "price": 1009,
          "star": 192,
          "url": "https://m.360buyimg.com/babel/s309x309_jfs/t1/110485/16/16014/90678/6151947fEe85cb718/bc3cd0d279e57efe.jpg!cc_501x501!q70.dpg"
        },
        {
          "id": "pop7",
          "tittle": "【刘亚仁同款】速写男装2021秋新品夹克明星同款水洗立领时尚潮9L9600360 990牛仔黑 M",
          "price": 2395,
          "star": 310,
          "url": "https://m.360buyimg.com/babel/s309x309_jfs/t1/199976/1/10682/424290/615557dbE25a5cb86/b939d3688e22e025.jpg!cc_501x501!q70.dpg"
        },
        {
          "id": "pop8",
          "tittle": "ONLY2021秋季新款杜邦三防中长款收腰90白鸭绒羽绒服女|121423005 H1Z 黑色BLACK 165/84A/M",
          "price": 1199,
          "star": 4000,
          "url": "https://m.360buyimg.com/babel/s309x309_jfs/t1/201407/7/8800/120721/6151a09eE7c5dfb56/c774006216420e37.jpg!cc_501x501!q70.dpg"
        },{
          "id": "pop9",
          "tittle": "【白宇帆明星同款】哈吉斯HAZZYS 2021秋冬新款中长款男士外套羽绒服男ASFZU01DX80Y 米色BI 175/96A",
          "price": 3391,
          "star": 1560,
          "url": "https://m.360buyimg.com/babel/s309x309_jfs/t1/206381/33/11993/6014/616fc634Ea138ff75/8d16edf00bd22f9d.jpg!cc_501x501!q70.dpg"
        },
        {
          "id": "pop10",
          "tittle": "Teenmix\/天美意短靴女厚底马丁靴女冬季2021新品商场同款靴子女单靴CZK40DD1 米色 37",
          "price": 1009,
          "star": 192,
          "url": "https://m.360buyimg.com/babel/s309x309_jfs/t1/110485/16/16014/90678/6151947fEe85cb718/bc3cd0d279e57efe.jpg!cc_501x501!q70.dpg"
        }
      ]
    },
    {
      "page": 2,
      "list": [
        {
          "id": "pop11",
          "tittle": "【白宇帆明星同款】哈吉斯HAZZYS 2021秋冬新款中长款男士外套羽绒服男ASFZU01DX80Y 米色BI 175/96A",
          "price": 3391,
          "star": 1560,
          "url": "https://m.360buyimg.com/babel/s309x309_jfs/t1/206381/33/11993/6014/616fc634Ea138ff75/8d16edf00bd22f9d.jpg!cc_501x501!q70.dpg"
        },
        {
          "id": "pop12",
          "tittle": "Teenmix\/天美意短靴女厚底马丁靴女冬季2021新品商场同款靴子女单靴CZK40DD1 米色 37",
          "price": 1009,
          "star": 192,
          "url": "https://m.360buyimg.com/babel/s309x309_jfs/t1/110485/16/16014/90678/6151947fEe85cb718/bc3cd0d279e57efe.jpg!cc_501x501!q70.dpg"
        },
        {
          "id": "pop13",
          "tittle": "【刘亚仁同款】速写男装2021秋新品夹克明星同款水洗立领时尚潮9L9600360 990牛仔黑 M",
          "price": 2395,
          "star": 310,
          "url": "https://m.360buyimg.com/babel/s309x309_jfs/t1/199976/1/10682/424290/615557dbE25a5cb86/b939d3688e22e025.jpg!cc_501x501!q70.dpg"
        },
        {
          "id": "pop14",
          "tittle": "ONLY2021秋季新款杜邦三防中长款收腰90白鸭绒羽绒服女|121423005 H1Z 黑色BLACK 165/84A/M",
          "price": 1199,
          "star": 4000,
          "url": "https://m.360buyimg.com/babel/s309x309_jfs/t1/201407/7/8800/120721/6151a09eE7c5dfb56/c774006216420e37.jpg!cc_501x501!q70.dpg"
        },
        {
          "id": "pop15",
          "tittle": "【白宇帆明星同款】哈吉斯HAZZYS 2021秋冬新款中长款男士外套羽绒服男ASFZU01DX80Y 米色BI 175/96A",
          "price": 3391,
          "star": 1560,
          "url": "https://m.360buyimg.com/babel/s309x309_jfs/t1/206381/33/11993/6014/616fc634Ea138ff75/8d16edf00bd22f9d.jpg!cc_501x501!q70.dpg"
        },
        {
          "id": "pop16",
          "tittle": "Teenmix\/天美意短靴女厚底马丁靴女冬季2021新品商场同款靴子女单靴CZK40DD1 米色 37",
          "price": 1009,
          "star": 192,
          "url": "https://m.360buyimg.com/babel/s309x309_jfs/t1/110485/16/16014/90678/6151947fEe85cb718/bc3cd0d279e57efe.jpg!cc_501x501!q70.dpg"
        },
        {
          "id": "pop17",
          "tittle": "【刘亚仁同款】速写男装2021秋新品夹克明星同款水洗立领时尚潮9L9600360 990牛仔黑 M",
          "price": 2395,
          "star": 310,
          "url": "https://m.360buyimg.com/babel/s309x309_jfs/t1/199976/1/10682/424290/615557dbE25a5cb86/b939d3688e22e025.jpg!cc_501x501!q70.dpg"
        },
        {
          "id": "pop18",
          "tittle": "ONLY2021秋季新款杜邦三防中长款收腰90白鸭绒羽绒服女|121423005 H1Z 黑色BLACK 165/84A/M",
          "price": 1199,
          "star": 4000,
          "url": "https://m.360buyimg.com/babel/s309x309_jfs/t1/201407/7/8800/120721/6151a09eE7c5dfb56/c774006216420e37.jpg!cc_501x501!q70.dpg"
        },{
          "id": "pop19",
          "tittle": "【白宇帆明星同款】哈吉斯HAZZYS 2021秋冬新款中长款男士外套羽绒服男ASFZU01DX80Y 米色BI 175/96A",
          "price": 3391,
          "star": 1560,
          "url": "https://m.360buyimg.com/babel/s309x309_jfs/t1/206381/33/11993/6014/616fc634Ea138ff75/8d16edf00bd22f9d.jpg!cc_501x501!q70.dpg"
        },
        {
          "id": "pop20",
          "tittle": "Teenmix\/天美意短靴女厚底马丁靴女冬季2021新品商场同款靴子女单靴CZK40DD1 米色 37",
          "price": 1009,
          "star": 192,
          "url": "https://m.360buyimg.com/babel/s309x309_jfs/t1/110485/16/16014/90678/6151947fEe85cb718/bc3cd0d279e57efe.jpg!cc_501x501!q70.dpg"
        }
      ]
    }
  ],
  "news": [
    {
      "page": 1,
      "list": [
        {
          "id": "news1",
          "tittle": "Teenmix\/天美意短靴女厚底马丁靴女冬季2021新品商场同款靴子女单靴CZK40DD1 米色 37",
          "price": 1009,
          "star": 192,
          "url": "https://m.360buyimg.com/babel/s309x309_jfs/t1/110485/16/16014/90678/6151947fEe85cb718/bc3cd0d279e57efe.jpg!cc_501x501!q70.dpg"
        },
        {
          "id": "news2",
          "tittle": "【白宇帆明星同款】哈吉斯HAZZYS 2021秋冬新款中长款男士外套羽绒服男ASFZU01DX80Y 米色BI 175/96A",
          "price": 3391,
          "star": 1560,
          "url": "https://m.360buyimg.com/babel/s309x309_jfs/t1/206381/33/11993/6014/616fc634Ea138ff75/8d16edf00bd22f9d.jpg!cc_501x501!q70.dpg"
        },
        {
          "id": "news3",
          "tittle": "ONLY2021秋季新款杜邦三防中长款收腰90白鸭绒羽绒服女|121423005 H1Z 黑色BLACK 165/84A/M",
          "price": 1199,
          "star": 4000,
          "url": "https://m.360buyimg.com/babel/s309x309_jfs/t1/201407/7/8800/120721/6151a09eE7c5dfb56/c774006216420e37.jpg!cc_501x501!q70.dpg"
        },
        {
          "id": "news4",
          "tittle": "【刘亚仁同款】速写男装2021秋新品夹克明星同款水洗立领时尚潮9L9600360 990牛仔黑 M",
          "price": 2395,
          "star": 310,
          "url": "https://m.360buyimg.com/babel/s309x309_jfs/t1/199976/1/10682/424290/615557dbE25a5cb86/b939d3688e22e025.jpg!cc_501x501!q70.dpg"
          
        },
        {
          "id": "news5",
          "tittle": "Teenmix\/天美意短靴女厚底马丁靴女冬季2021新品商场同款靴子女单靴CZK40DD1 米色 37",
          "price": 1009,
          "star": 192,
          "url": "https://m.360buyimg.com/babel/s309x309_jfs/t1/110485/16/16014/90678/6151947fEe85cb718/bc3cd0d279e57efe.jpg!cc_501x501!q70.dpg"
        },
        {
          "id": "news6",
          "tittle": "【白宇帆明星同款】哈吉斯HAZZYS 2021秋冬新款中长款男士外套羽绒服男ASFZU01DX80Y 米色BI 175/96A",
          "price": 3391,
          "star": 1560,
          "url": "https://m.360buyimg.com/babel/s309x309_jfs/t1/206381/33/11993/6014/616fc634Ea138ff75/8d16edf00bd22f9d.jpg!cc_501x501!q70.dpg"
        },
        {
          "id": "news7",
          "tittle": "ONLY2021秋季新款杜邦三防中长款收腰90白鸭绒羽绒服女|121423005 H1Z 黑色BLACK 165/84A/M",
          "price": 1199,
          "star": 4000,
          "url": "https://m.360buyimg.com/babel/s309x309_jfs/t1/201407/7/8800/120721/6151a09eE7c5dfb56/c774006216420e37.jpg!cc_501x501!q70.dpg"
        },
        {
          "id": "news8",
          "tittle": "【刘亚仁同款】速写男装2021秋新品夹克明星同款水洗立领时尚潮9L9600360 990牛仔黑 M",
          "price": 2395,
          "star": 310,
          "url": "https://m.360buyimg.com/babel/s309x309_jfs/t1/199976/1/10682/424290/615557dbE25a5cb86/b939d3688e22e025.jpg!cc_501x501!q70.dpg"
        },
        {
          "id": "news9",
          "tittle": "【白宇帆明星同款】哈吉斯HAZZYS 2021秋冬新款中长款男士外套羽绒服男ASFZU01DX80Y 米色BI 175/96A",
          "price": 3391,
          "star": 1560,
          "url": "https://m.360buyimg.com/babel/s309x309_jfs/t1/206381/33/11993/6014/616fc634Ea138ff75/8d16edf00bd22f9d.jpg!cc_501x501!q70.dpg"
        },
        {
          "id": "news10",
          "tittle": "Teenmix\/天美意短靴女厚底马丁靴女冬季2021新品商场同款靴子女单靴CZK40DD1 米色 37",
          "price": 1009,
          "star": 192,
          "url": "https://m.360buyimg.com/babel/s309x309_jfs/t1/110485/16/16014/90678/6151947fEe85cb718/bc3cd0d279e57efe.jpg!cc_501x501!q70.dpg"
        }
      ]
    },
    {
      "page": 2,
      "list": [
        {
          "id": "news11",
          "tittle": "【白宇帆明星同款】哈吉斯HAZZYS 2021秋冬新款中长款男士外套羽绒服男ASFZU01DX80Y 米色BI 175/96A",
          "price": 3391,
          "star": 1560,
          "url": "https://m.360buyimg.com/babel/s309x309_jfs/t1/206381/33/11993/6014/616fc634Ea138ff75/8d16edf00bd22f9d.jpg!cc_501x501!q70.dpg"
        },
        {
          "id": "news12",
          "tittle": "Teenmix\/天美意短靴女厚底马丁靴女冬季2021新品商场同款靴子女单靴CZK40DD1 米色 37",
          "price": 1009,
          "star": 192,
          "url": "https://m.360buyimg.com/babel/s309x309_jfs/t1/110485/16/16014/90678/6151947fEe85cb718/bc3cd0d279e57efe.jpg!cc_501x501!q70.dpg"
        },
        {
          "id": "news13",
          "tittle": "【刘亚仁同款】速写男装2021秋新品夹克明星同款水洗立领时尚潮9L9600360 990牛仔黑 M",
          "price": 2395,
          "star": 310,
          "url": "https://m.360buyimg.com/babel/s309x309_jfs/t1/199976/1/10682/424290/615557dbE25a5cb86/b939d3688e22e025.jpg!cc_501x501!q70.dpg"
        },
        {
          "id": "news14",
          "tittle": "ONLY2021秋季新款杜邦三防中长款收腰90白鸭绒羽绒服女|121423005 H1Z 黑色BLACK 165/84A/M",
          "price": 1199,
          "star": 4000,
          "url": "https://m.360buyimg.com/babel/s309x309_jfs/t1/201407/7/8800/120721/6151a09eE7c5dfb56/c774006216420e37.jpg!cc_501x501!q70.dpg"
        },
        {
          "id": "news15",
          "tittle": "【白宇帆明星同款】哈吉斯HAZZYS 2021秋冬新款中长款男士外套羽绒服男ASFZU01DX80Y 米色BI 175/96A",
          "price": 3391,
          "star": 1560,
          "url": "https://m.360buyimg.com/babel/s309x309_jfs/t1/206381/33/11993/6014/616fc634Ea138ff75/8d16edf00bd22f9d.jpg!cc_501x501!q70.dpg"
        },
        {
          "id": "news16",
          "tittle": "Teenmix\/天美意短靴女厚底马丁靴女冬季2021新品商场同款靴子女单靴CZK40DD1 米色 37",
          "price": 1009,
          "star": 192,
          "url": "https://m.360buyimg.com/babel/s309x309_jfs/t1/110485/16/16014/90678/6151947fEe85cb718/bc3cd0d279e57efe.jpg!cc_501x501!q70.dpg"
        },
        {
          "id": "news17",
          "tittle": "【刘亚仁同款】速写男装2021秋新品夹克明星同款水洗立领时尚潮9L9600360 990牛仔黑 M",
          "price": 2395,
          "star": 310,
          "url": "https://m.360buyimg.com/babel/s309x309_jfs/t1/199976/1/10682/424290/615557dbE25a5cb86/b939d3688e22e025.jpg!cc_501x501!q70.dpg"
        },
        {
          "id": "news18",
          "tittle": "ONLY2021秋季新款杜邦三防中长款收腰90白鸭绒羽绒服女|121423005 H1Z 黑色BLACK 165/84A/M",
          "price": 1199,
          "star": 4000,
          "url": "https://m.360buyimg.com/babel/s309x309_jfs/t1/201407/7/8800/120721/6151a09eE7c5dfb56/c774006216420e37.jpg!cc_501x501!q70.dpg"
        },{
          "id": "news19",
          "tittle": "【白宇帆明星同款】哈吉斯HAZZYS 2021秋冬新款中长款男士外套羽绒服男ASFZU01DX80Y 米色BI 175/96A",
          "price": 3391,
          "star": 1560,
          "url": "https://m.360buyimg.com/babel/s309x309_jfs/t1/206381/33/11993/6014/616fc634Ea138ff75/8d16edf00bd22f9d.jpg!cc_501x501!q70.dpg"
        },
        {
          "id": "news20",
          "tittle": "Teenmix\/天美意短靴女厚底马丁靴女冬季2021新品商场同款靴子女单靴CZK40DD1 米色 37",
          "price": 1009,
          "star": 192,
          "url": "https://m.360buyimg.com/babel/s309x309_jfs/t1/110485/16/16014/90678/6151947fEe85cb718/bc3cd0d279e57efe.jpg!cc_501x501!q70.dpg"
        }
      ]
    }
  ],
  "sell": [
    {
      "page": 1,
      "list": [
        {
          "id": "sell1",
          "tittle": "【刘亚仁同款】速写男装2021秋新品夹克明星同款水洗立领时尚潮9L9600360 990牛仔黑 M",
          "price": 2395,
          "star": 310,
          "url": "https://m.360buyimg.com/babel/s309x309_jfs/t1/199976/1/10682/424290/615557dbE25a5cb86/b939d3688e22e025.jpg!cc_501x501!q70.dpg"
        },
        {
          "id": "sell2",
          "tittle": "ONLY2021秋季新款杜邦三防中长款收腰90白鸭绒羽绒服女|121423005 H1Z 黑色BLACK 165/84A/M",
          "price": 1199,
          "star": 4000,
          "url": "https://m.360buyimg.com/babel/s309x309_jfs/t1/201407/7/8800/120721/6151a09eE7c5dfb56/c774006216420e37.jpg!cc_501x501!q70.dpg"
        },
        {
          "id": "sell3",
          "tittle": "【白宇帆明星同款】哈吉斯HAZZYS 2021秋冬新款中长款男士外套羽绒服男ASFZU01DX80Y 米色BI 175/96A",
          "price": 3391,
          "star": 1560,
          "url": "https://m.360buyimg.com/babel/s309x309_jfs/t1/206381/33/11993/6014/616fc634Ea138ff75/8d16edf00bd22f9d.jpg!cc_501x501!q70.dpg"
        },
        {
          "id": "sell4",
          "tittle": "Teenmix\/天美意短靴女厚底马丁靴女冬季2021新品商场同款靴子女单靴CZK40DD1 米色 37",
          "price": 1009,
          "star": 192,
          "url": "https://m.360buyimg.com/babel/s309x309_jfs/t1/110485/16/16014/90678/6151947fEe85cb718/bc3cd0d279e57efe.jpg!cc_501x501!q70.dpg"
        },
        {
          "id": "sell5",
          "tittle": "【刘亚仁同款】速写男装2021秋新品夹克明星同款水洗立领时尚潮9L9600360 990牛仔黑 M",
          "price": 2395,
          "star": 310,
          "url": "https://m.360buyimg.com/babel/s309x309_jfs/t1/199976/1/10682/424290/615557dbE25a5cb86/b939d3688e22e025.jpg!cc_501x501!q70.dpg"
        },
        {
          "id": "sell6",
          "tittle": "ONLY2021秋季新款杜邦三防中长款收腰90白鸭绒羽绒服女|121423005 H1Z 黑色BLACK 165/84A/M",
          "price": 1199,
          "star": 4000,
          "url": "https://m.360buyimg.com/babel/s309x309_jfs/t1/201407/7/8800/120721/6151a09eE7c5dfb56/c774006216420e37.jpg!cc_501x501!q70.dpg"
        },
        {
          "id": "sell7",
          "tittle": "【白宇帆明星同款】哈吉斯HAZZYS 2021秋冬新款中长款男士外套羽绒服男ASFZU01DX80Y 米色BI 175/96A",
          "price": 3391,
          "star": 1560,
          "url": "https://m.360buyimg.com/babel/s309x309_jfs/t1/206381/33/11993/6014/616fc634Ea138ff75/8d16edf00bd22f9d.jpg!cc_501x501!q70.dpg"
        },
        {
          "id": "sell8",
          "tittle": "Teenmix\/天美意短靴女厚底马丁靴女冬季2021新品商场同款靴子女单靴CZK40DD1 米色 37",
          "price": 1009,
          "star": 192,
          "url": "https://m.360buyimg.com/babel/s309x309_jfs/t1/110485/16/16014/90678/6151947fEe85cb718/bc3cd0d279e57efe.jpg!cc_501x501!q70.dpg"
        },
        {
          "id": "sell9",
          "tittle": "【白宇帆明星同款】哈吉斯HAZZYS 2021秋冬新款中长款男士外套羽绒服男ASFZU01DX80Y 米色BI 175/96A",
          "price": 3391,
          "star": 1560,
          "url": "https://m.360buyimg.com/babel/s309x309_jfs/t1/206381/33/11993/6014/616fc634Ea138ff75/8d16edf00bd22f9d.jpg!cc_501x501!q70.dpg"
        },
        {
          "id": "sell10",
          "tittle": "Teenmix\/天美意短靴女厚底马丁靴女冬季2021新品商场同款靴子女单靴CZK40DD1 米色 37",
          "price": 1009,
          "star": 192,
          "url": "https://m.360buyimg.com/babel/s309x309_jfs/t1/110485/16/16014/90678/6151947fEe85cb718/bc3cd0d279e57efe.jpg!cc_501x501!q70.dpg"
        }
      ]
    },
    {
      "page": 2,
      "list": [
        {
          "id": "sell11",
          "tittle": "【白宇帆明星同款】哈吉斯HAZZYS 2021秋冬新款中长款男士外套羽绒服男ASFZU01DX80Y 米色BI 175/96A",
          "price": 3391,
          "star": 1560,
          "url": "https://m.360buyimg.com/babel/s309x309_jfs/t1/206381/33/11993/6014/616fc634Ea138ff75/8d16edf00bd22f9d.jpg!cc_501x501!q70.dpg"
        },
        {
          "id": "sell12",
          "tittle": "Teenmix\/天美意短靴女厚底马丁靴女冬季2021新品商场同款靴子女单靴CZK40DD1 米色 37",
          "price": 1009,
          "star": 192,
          "url": "https://m.360buyimg.com/babel/s309x309_jfs/t1/110485/16/16014/90678/6151947fEe85cb718/bc3cd0d279e57efe.jpg!cc_501x501!q70.dpg"
        },
        {
          "id": "sell13",
          "tittle": "【刘亚仁同款】速写男装2021秋新品夹克明星同款水洗立领时尚潮9L9600360 990牛仔黑 M",
          "price": 2395,
          "star": 310,
          "url": "https://m.360buyimg.com/babel/s309x309_jfs/t1/199976/1/10682/424290/615557dbE25a5cb86/b939d3688e22e025.jpg!cc_501x501!q70.dpg"
        },
        {
          "id": "sell14",
          "tittle": "ONLY2021秋季新款杜邦三防中长款收腰90白鸭绒羽绒服女|121423005 H1Z 黑色BLACK 165/84A/M",
          "price": 1199,
          "star": 4000,
          "url": "https://m.360buyimg.com/babel/s309x309_jfs/t1/201407/7/8800/120721/6151a09eE7c5dfb56/c774006216420e37.jpg!cc_501x501!q70.dpg"
        },
        {
          "id": "sell15",
          "tittle": "【白宇帆明星同款】哈吉斯HAZZYS 2021秋冬新款中长款男士外套羽绒服男ASFZU01DX80Y 米色BI 175/96A",
          "price": 3391,
          "star": 1560,
          "url": "https://m.360buyimg.com/babel/s309x309_jfs/t1/206381/33/11993/6014/616fc634Ea138ff75/8d16edf00bd22f9d.jpg!cc_501x501!q70.dpg"
        },
        {
          "id": "sell16",
          "tittle": "Teenmix\/天美意短靴女厚底马丁靴女冬季2021新品商场同款靴子女单靴CZK40DD1 米色 37",
          "price": 1009,
          "star": 192,
          "url": "https://m.360buyimg.com/babel/s309x309_jfs/t1/110485/16/16014/90678/6151947fEe85cb718/bc3cd0d279e57efe.jpg!cc_501x501!q70.dpg"
        },
        {
          "id": "sell17",
          "tittle": "【刘亚仁同款】速写男装2021秋新品夹克明星同款水洗立领时尚潮9L9600360 990牛仔黑 M",
          "price": 2395,
          "star": 310,
          "url": "https://m.360buyimg.com/babel/s309x309_jfs/t1/199976/1/10682/424290/615557dbE25a5cb86/b939d3688e22e025.jpg!cc_501x501!q70.dpg"
        },
        {
          "id": "sell18",
          "tittle": "ONLY2021秋季新款杜邦三防中长款收腰90白鸭绒羽绒服女|121423005 H1Z 黑色BLACK 165/84A/M",
          "price": 1199,
          "star": 4000,
          "url": "https://m.360buyimg.com/babel/s309x309_jfs/t1/201407/7/8800/120721/6151a09eE7c5dfb56/c774006216420e37.jpg!cc_501x501!q70.dpg"
        },{
          "id": "sell19",
          "tittle": "【白宇帆明星同款】哈吉斯HAZZYS 2021秋冬新款中长款男士外套羽绒服男ASFZU01DX80Y 米色BI 175/96A",
          "price": 3391,
          "star": 1560,
          "url": "https://m.360buyimg.com/babel/s309x309_jfs/t1/206381/33/11993/6014/616fc634Ea138ff75/8d16edf00bd22f9d.jpg!cc_501x501!q70.dpg"
        },
        {
          "id": "sell20",
          "tittle": "Teenmix\/天美意短靴女厚底马丁靴女冬季2021新品商场同款靴子女单靴CZK40DD1 米色 37",
          "price": 1009,
          "star": 192,
          "url": "https://m.360buyimg.com/babel/s309x309_jfs/t1/110485/16/16014/90678/6151947fEe85cb718/bc3cd0d279e57efe.jpg!cc_501x501!q70.dpg"
        }
      ]
    }
  ]
}